aafp_database_connection/__init__.py
aafp_database_connection/databaseConnection.py
aafp_database_connection/databaseConnectionFactory.py
aafp_database_connection/databaseConnectionInflux.py
database_connection/__init__.py
database_connection/databaseConnection.py
database_connection/databaseConnectionFactory.py
database_connection/databaseConnectionInflux.py
aafp_database_connection-0.1.dist-info/LICENSE
aafp_database_connection-0.1.dist-info/METADATA
aafp_database_connection-0.1.dist-info/WHEEL
aafp_database_connection-0.1.dist-info/top_level.txt
aafp_database_connection-0.1.dist-info/RECORD
