Metadata-Version: 2.1
Name: aafp-database-connection
Version: 0.1
Summary: Connection to a database e.g. influx
Home-page: https://github.com/AnnAnnFryingPan/aafp_database_connection
Author: Ann Gledson
Author-email: anngledson@gmail.com
License: MIT
Platform: UNKNOWN
